crowbar_reference_compiler/__init__.py
crowbar_reference_compiler/ast.py
crowbar_reference_compiler/parser.py
crowbar_reference_compiler/scanner.py
crowbar_reference_compiler/ssagen.py
crowbar_reference_compiler-0.0.6.dist-info/entry_points.txt
crowbar_reference_compiler-0.0.6.dist-info/LICENSE.md
crowbar_reference_compiler-0.0.6.dist-info/WHEEL
crowbar_reference_compiler-0.0.6.dist-info/METADATA
crowbar_reference_compiler-0.0.6.dist-info/RECORD
