Metadata-Version: 2.1
Name: crowbar-reference-compiler
Version: 0.0.6
Summary: the reference compiler for the Crowbar programming language
Home-page: https://git.sr.ht/~boringcactus/crowbar-reference-compiler
License: BlueOak-1.0.0
Author: Melody Horn
Author-email: melody@boringcactus.com
Requires-Python: >=3.7,<4.0
Classifier: Development Status :: 2 - Pre-Alpha
Classifier: Intended Audience :: Developers
Classifier: License :: Other/Proprietary License
Classifier: Programming Language :: Other
Classifier: Programming Language :: Python :: 3
Classifier: Programming Language :: Python :: 3.7
Classifier: Programming Language :: Python :: 3.8
Classifier: Programming Language :: Python :: 3.9
Classifier: Topic :: Software Development :: Compilers
Requires-Dist: parsimonious (>=0.8.1,<0.9.0)
Requires-Dist: regex (>=2020.10.11,<2021.0.0)
Project-URL: Repository, https://git.sr.ht/~boringcactus/crowbar-reference-compiler
